Workbook

Sheet Assumptions
A1: Kabadiwala Connect: Unit Economics & Model Assumptions
A3: Parameter / Scrap Category | B3: Baseline Daily Volume (kg) | C3: Informal Middleman Rate (₹/kg) | D3: Formal Recycler Benchmark (₹/kg) | E3: Middleman Haircut (%) | F3: Data Provenance / Status | G3: Fill from Field Action (Collector Interviews)
A4: CRT Monitors / TVs | B4: 8 | C4: 9.5 | D4: 13.5 | E4: =(D4-C4)/D4 | F4: Assumption | G4: Replace with measured daily kg from Interview #1
A5: LCD Panels & Assemblies | B5: 4 | C5: 32 | D5: 46 | E5: =(D5-C5)/D5 | F5: Assumption | G5: Verify screen buying rate from scrap yard visits
A6: PCB (Low Grade - Power Supplies) | B6: 5 | C6: 35 | D6: 50 | E6: =(D6-C6)/D6 | F6: Assumption | G6: Replace with local aggregator quote
A7: PCB (Mid Grade - Motherboards) | B7: 3 | C7: 145 | D7: 205 | E7: =(D7-C7)/D7 | F7: Field-Verified (Thane) | G7: Cross-check with Thane field baseline
A8: PCB (High Grade - Mobile/Server) | B8: 1.5 | C8: 420 | D8: 610 | E8: =(D8-C8)/D8 | F8: Field-Verified (Kurla) | G8: Verify against formal smelter lot quote
A9: Copper Cables & Wiring | B9: 6 | C9: 215 | D9: 305 | E9: =(D9-C9)/D9 | F9: Field-Verified (Dharavi) | G9: Record actual unstripped cable price
A10: Li-ion & Lead-Acid Batteries | B10: 4.5 | C10: 65 | D10: 92 | E10: =(D10-C10)/D10 | F10: Assumption | G10: Verify hazardous battery rate
A11: Motors, Transformers & Magnets | B11: 6 | C11: 58 | D11: 82 | E11: =(D11-C11)/D11 | F11: Assumption | G11: Verify copper recovery deductions
A12: Mixed E-Waste Plastics (ABS/HIPS) | B12: 5 | C12: 15 | D12: 23 | E12: =(D12-C12)/D12 | F12: Assumption | G12: Confirm clean sorted plastic price
A13: Total Daily E-Waste Collected (kg) | B13: =SUM(B4:B12) | C13: - | D13: - | E13: - | F13: - | G13: Total daily collection capacity
A16: General Operational Assumptions
A17: Working Days per Month | B17: 26 | C17: Days | F17: Assumption | G17: Confirm actual working days from interview
A18: Monthly Informal Health & Fines Burden | B18: 850 | C18: ₹ / month | F18: Assumption | G18: Cost of burn treatments, toxic cough syrup & police fines
A19: Conservative Price Improvement | B19: 0.1 | C19: % | F19: Scenario Assumption | G19: Platform gain: 10% price lift
A20: Conservative Volume Increase | B20: 0.2 | C20: % | F20: Scenario Assumption | G20: Platform gain: 20% volume growth (pickup routing)
A21: Base Price Improvement | B21: 0.25 | C21: % | F21: Scenario Assumption | G21: Platform gain: 25% price lift
A22: Base Volume Increase | B22: 0.4 | C22: % | F22: Scenario Assumption | G22: Platform gain: 40% volume growth
A23: Optimistic Price Improvement | B23: 0.35 | C23: % | F23: Scenario Assumption | G23: Platform gain: 35% price lift
A24: Optimistic Volume Increase | B24: 0.6 | C24: % | F24: Scenario Assumption | G24: Platform gain: 60% volume growth

Sheet Collector Economics
A1: Collector Income Delta: Baseline (Informal) vs Platform Scenarios
A3: Scrap Category | B3: Baseline Daily (₹) | C3: Conservative Daily (₹) | D3: Base Daily (₹) | E3: Optimistic Daily (₹) | F3: Base Daily Lift (₹) | G3: Base % Lift | H3: Remarks & Impact Drivers
A4: =Assumptions!A4 | B4: =Assumptions!B4*Assumptions!C4 | C4: =(Assumptions!B4*(1+Assumptions!$B$19))*(Assumptions!C4*(1+Assumptions!$B$18)) | D4: =(Assumptions!B4*(1+Assumptions!$B$21))*(Assumptions!C4*(1+Assumptions!$B$20)) | E4: =(Assumptions!B4*(1+Assumptions!$B$23))*(Assumptions!C4*(1+Assumptions!$B$22)) | F4: =D4-B4 | G4: =F4/B4 | H4: Direct formal market rate without middleman haircut
A5: =Assumptions!A5 | B5: =Assumptions!B5*Assumptions!C5 | C5: =(Assumptions!B5*(1+Assumptions!$B$19))*(Assumptions!C5*(1+Assumptions!$B$18)) | D5: =(Assumptions!B5*(1+Assumptions!$B$21))*(Assumptions!C5*(1+Assumptions!$B$20)) | E5: =(Assumptions!B5*(1+Assumptions!$B$23))*(Assumptions!C5*(1+Assumptions!$B$22)) | F5: =D5-B5 | G5: =F5/B5 | H5: Direct formal market rate without middleman haircut
A6: =Assumptions!A6 | B6: =Assumptions!B6*Assumptions!C6 | C6: =(Assumptions!B6*(1+Assumptions!$B$19))*(Assumptions!C6*(1+Assumptions!$B$18)) | D6: =(Assumptions!B6*(1+Assumptions!$B$21))*(Assumptions!C6*(1+Assumptions!$B$20)) | E6: =(Assumptions!B6*(1+Assumptions!$B$23))*(Assumptions!C6*(1+Assumptions!$B$22)) | F6: =D6-B6 | G6: =F6/B6 | H6: Direct formal market rate without middleman haircut
A7: =Assumptions!A7 | B7: =Assumptions!B7*Assumptions!C7 | C7: =(Assumptions!B7*(1+Assumptions!$B$19))*(Assumptions!C7*(1+Assumptions!$B$18)) | D7: =(Assumptions!B7*(1+Assumptions!$B$21))*(Assumptions!C7*(1+Assumptions!$B$20)) | E7: =(Assumptions!B7*(1+Assumptions!$B$23))*(Assumptions!C7*(1+Assumptions!$B$22)) | F7: =D7-B7 | G7: =F7/B7 | H7: Direct formal market rate without middleman haircut
A8: =Assumptions!A8 | B8: =Assumptions!B8*Assumptions!C8 | C8: =(Assumptions!B8*(1+Assumptions!$B$19))*(Assumptions!C8*(1+Assumptions!$B$18)) | D8: =(Assumptions!B8*(1+Assumptions!$B$21))*(Assumptions!C8*(1+Assumptions!$B$20)) | E8: =(Assumptions!B8*(1+Assumptions!$B$23))*(Assumptions!C8*(1+Assumptions!$B$22)) | F8: =D8-B8 | G8: =F8/B8 | H8: Direct formal market rate without middleman haircut
A9: =Assumptions!A9 | B9: =Assumptions!B9*Assumptions!C9 | C9: =(Assumptions!B9*(1+Assumptions!$B$19))*(Assumptions!C9*(1+Assumptions!$B$18)) | D9: =(Assumptions!B9*(1+Assumptions!$B$21))*(Assumptions!C9*(1+Assumptions!$B$20)) | E9: =(Assumptions!B9*(1+Assumptions!$B$23))*(Assumptions!C9*(1+Assumptions!$B$22)) | F9: =D9-B9 | G9: =F9/B9 | H9: Direct formal market rate without middleman haircut
A10: =Assumptions!A10 | B10: =Assumptions!B10*Assumptions!C10 | C10: =(Assumptions!B10*(1+Assumptions!$B$19))*(Assumptions!C10*(1+Assumptions!$B$18)) | D10: =(Assumptions!B10*(1+Assumptions!$B$21))*(Assumptions!C10*(1+Assumptions!$B$20)) | E10: =(Assumptions!B10*(1+Assumptions!$B$23))*(Assumptions!C10*(1+Assumptions!$B$22)) | F10: =D10-B10 | G10: =F10/B10 | H10: Direct formal market rate without middleman haircut
A11: =Assumptions!A11 | B11: =Assumptions!B11*Assumptions!C11 | C11: =(Assumptions!B11*(1+Assumptions!$B$19))*(Assumptions!C11*(1+Assumptions!$B$18)) | D11: =(Assumptions!B11*(1+Assumptions!$B$21))*(Assumptions!C11*(1+Assumptions!$B$20)) | E11: =(Assumptions!B11*(1+Assumptions!$B$23))*(Assumptions!C11*(1+Assumptions!$B$22)) | F11: =D11-B11 | G11: =F11/B11 | H11: Direct formal market rate without middleman haircut
A12: =Assumptions!A12 | B12: =Assumptions!B12*Assumptions!C12 | C12: =(Assumptions!B12*(1+Assumptions!$B$19))*(Assumptions!C12*(1+Assumptions!$B$18)) | D12: =(Assumptions!B12*(1+Assumptions!$B$21))*(Assumptions!C12*(1+Assumptions!$B$20)) | E12: =(Assumptions!B12*(1+Assumptions!$B$23))*(Assumptions!C12*(1+Assumptions!$B$22)) | F12: =D12-B12 | G12: =F12/B12 | H12: Direct formal market rate without middleman haircut
A13: TOTAL DAILY GROSS EARNINGS (₹) | B13: =SUM(B4:B12) | C13: =SUM(C4:C12) | D13: =SUM(D4:D12) | E13: =SUM(E4:E12) | F13: =D13-B13 | G13: =(D13-B13)/B13 | H13: Net daily earnings across all categories
A16: Monthly Collector Income & Living Standard Comparison
A17: Metric | B17: Baseline (Informal) | C17: Conservative (Platform) | D17: Base Case (Platform) | E17: Optimistic (Platform) | F17: Base Monthly Delta | G17: Growth % | H17: Economic & Social Impact
A18: Monthly Gross Scrap Revenue (26 Days) | B18: =B13*Assumptions!$B$16 | C18: =C13*Assumptions!$B$16 | D18: =D13*Assumptions!$B$16 | E18: =E13*Assumptions!$B$16 | F18: =D18-B18 | G18: =(D18-B18)/B18 | H18: Calculated from 26 working collection days per month
A19: Less: Health, Burn Injuries & Fine Burden | B19: =-Assumptions!$B$17 | C19: =-Assumptions!$B$17*0.4 | D19: =-Assumptions!$B$17*0.2 | E19: =0 | F19: =D19-B19 | G19: =(D19-B19)/(-B19) | H19: Safety instructions & formal channels eliminate backyard acid/fire risks
A20: NET MONTHLY TAKE-HOME INCOME (₹) | B20: =B18+B19 | C20: =C18+C19 | D20: =D18+D19 | E20: =E18+E19 | F20: =D20-B20 | G20: =(D20-B20)/B20 | H20: Transformative income lift lifting collector families above poverty line

Sheet Platform Sustainability
A1: Platform Unit Economics, Revenue Streams & Break-Even Model
A3: Revenue Stream / Cost Driver | B3: Unit Rate / Basis | C3: Monthly Volume Units | D3: Monthly Revenue / Cost (₹) | E3: % of Total | F3: Provenance / Status | G3: Model Notes & Scaling Assumption
A4: 1. Recycler SaaS Portal Subscription | B4: 500 | C4: ₹ / recycler / mo | D4: 100 | E4: =B4*D4 | F4: Assumption | G4: 100 authorized EPR aggregators across Maharashtra
A5: 2. Marketplace Transaction Commission | B5: 0.015 | C5: 1.5% of gross trade | D5: 5850000 | E5: =B5*D5 | F5: Assumption | G5: Gross transaction volume of ~130 MT/mo across 1,000 collectors
A6: 3. EPR Compliance Traceability Certificate Fee | B6: 1.2 | C6: ₹ / verified kg | D6: 130000 | E6: =B6*D6 | F6: Assumption | G6: Brand Producer EPR compliance credits (CPCB verified portal)
A7: 4. Government / CSR Innovation & Safety Grant | B7: 25000 | C7: ₹ / month fixed | D7: 1 | E7: =B7*D7 | F7: Assumption | G7: Ministry of Mines / JNARDDC informal sector formalization grant
A8: TOTAL MONTHLY REVENUE (₹) | B8: - | C8: - | D8: - | E8: =SUM(E4:E7) | F8: 100.0% | G8: Total blended platform revenue
A10: Monthly Operational Cost Structure (OPEX)
A11: Cloud Infrastructure (PostGIS, FastAPI, Next.js Hosting) | B11: 8500 | C11: Monthly AWS/GCP hosting | D11: 1 | E11: =B11 | F11: Assumption | G11: High availability, spatial indexing & auto-scaling
A12: SMS OTP & Vernacular Speech Engine API | B12: 3500 | C12: Monthly API quota | D12: 1 | E12: =B12 | F12: Assumption | G12: Pluggable OTP verification & high-quality Devanagari TTS
A13: Ground Field Coordinators & Recycler Support (2 Staff) | B13: 50000 | C13: Staff honorarium | D13: 1 | E13: =B13 | F13: Assumption | G13: Scrap cluster outreach, weight verification audits & onboarding
A14: Software Maintenance, ML Drift Retraining & Bugfixes | B14: 25000 | C14: Dev team allocation | D14: 1 | E14: =B14 | F14: Assumption | G14: Monthly retraining of pricing & anomaly detection pipelines
A15: EPR Regulatory Audit & Compliance Certification Filing | B15: 12000 | C15: Auditor compliance | D15: 1 | E15: =B15 | F15: Assumption | G15: Annual third-party mass balance validation
A16: TOTAL MONTHLY OPERATIONAL COSTS (₹) | B16: - | C16: - | D16: - | E16: =SUM(E11:E15) | F16: - | G16: Total monthly operating budget
A17: NET MONTHLY OPERATING MARGIN / SURPLUS (₹) | B17: - | C17: - | D17: - | E17: =E8-E16 | F17: =(E8-E16)/E8 | G17: Sustainable unit economics for long-term nationwide deployment
A21: Sensitivity Analysis: Recycler Adoption Pace (Year 1 Scenarios)
A22: Adoption Scenario | B22: Active Recyclers | C22: Monthly Volume (kg) | D22: Monthly Revenue (₹) | E22: Monthly OPEX (₹) | F22: Net Surplus / (Deficit) (₹) | G22: Status & Breakeven Point
A23: Slow Adoption (Year 1 Cold Start) | B23: 20 | C23: 26000 | D23: =(20*500)+(26000*45*0.015)+(26000*1.2)+25000 | E23: =E16*0.8 | F23: =D23-E23 | G23: Breakeven via Grant Support
A24: Moderate Adoption (Mid Year 1) | B24: 50 | C24: 65000 | D24: =(50*500)+(65000*45*0.015)+(65000*1.2)+25000 | E24: =E16*0.9 | F24: =D24-E24 | G24: Profitable Operations
A25: Target Adoption (Year 1 Goal) | B25: 100 | C25: 130000 | D25: =E8 | E25: =E16 | F25: =D25-E25 | G25: Target Operating Model
A26: High Expansion (Year 2 Scale) | B26: 250 | C26: 350000 | D26: =(250*500)+(350000*45*0.015)+(350000*1.2)+25000 | E26: =E16*1.4 | F26: =D26-E26 | G26: High Surplus for Collector Welfare Fund
